{"is_source_file": false, "format": "", "description": "", "external_files": [], "external_methods": [], "published": [], "classes": [], "methods": [], "calls": [], "search-terms": [], "state": 2, "file_id": 47, "knowledge_revision": 245, "git_revision": "fc96e5f98ad94fdcea96258357d4f29d8004640e", "hash": "ca6b36c302dbd20c4718a5124a511711", "format-version": 4, "code-base-name": "frontend_lms", "filename": "frontend_lms/src/content/internship_letter.md", "revision_history": [{"245": "fc96e5f98ad94fdcea96258357d4f29d8004640e"}]}